wavestate/pytest/__init__.py
wavestate/pytest/_version.py
wavestate/pytest/fixtures.py
wavestate/pytest/utilities.py
wavestate/pytest/test/test_fixtures.py
wavestate.pytest-0.9.1.dist-info/METADATA
wavestate.pytest-0.9.1.dist-info/NOTICE
wavestate.pytest-0.9.1.dist-info/WHEEL
wavestate.pytest-0.9.1.dist-info/top_level.txt
wavestate.pytest-0.9.1.dist-info/RECORD
